Undefined/__init__.py
Undefined/__main__.py
Undefined/config.py
Undefined/context.py
Undefined/context_resource_registry.py
Undefined/end_summary_storage.py
Undefined/faq.py
Undefined/handlers.py
Undefined/injection_response_agent.py
Undefined/main.py
Undefined/memory.py
Undefined/onebot.py
Undefined/rate_limit.py
Undefined/render.py
Undefined/scheduled_task_storage.py
Undefined/token_usage_storage.py
Undefined/ai/__init__.py
Undefined/ai/client.py
Undefined/ai/http.py
Undefined/ai/multimodal.py
Undefined/ai/parsing.py
Undefined/ai/prompts.py
Undefined/ai/summaries.py
Undefined/ai/tokens.py
Undefined/ai/tooling.py
Undefined/mcp/__init__.py
Undefined/mcp/registry.py
Undefined/services/__init__.py
Undefined/services/ai_coordinator.py
Undefined/services/command.py
Undefined/services/queue_manager.py
Undefined/services/security.py
Undefined/skills/README.md
Undefined/skills/__init__.py
Undefined/skills/registry.py
Undefined/skills/agents/README.md
Undefined/skills/agents/__init__.py
Undefined/skills/agents/agent_tool_registry.py
Undefined/skills/agents/intro_generator.py
Undefined/skills/agents/intro_utils.py
Undefined/skills/agents/entertainment_agent/config.json
Undefined/skills/agents/entertainment_agent/handler.py
Undefined/skills/agents/entertainment_agent/intro.md
Undefined/skills/agents/entertainment_agent/prompt.md
Undefined/skills/agents/entertainment_agent/tools/__init__.py
Undefined/skills/agents/entertainment_agent/tools/ai_draw_one/config.json
Undefined/skills/agents/entertainment_agent/tools/ai_draw_one/handler.py
Undefined/skills/agents/entertainment_agent/tools/ai_study_helper/config.json
Undefined/skills/agents/entertainment_agent/tools/ai_study_helper/handler.py
Undefined/skills/agents/entertainment_agent/tools/get_current_time/config.json
Undefined/skills/agents/entertainment_agent/tools/get_current_time/handler.py
Undefined/skills/agents/entertainment_agent/tools/horoscope/config.json
undefined_bot-2.9.0.dist-info/METADATA
undefined_bot-2.9.0.dist-info/WHEEL
undefined_bot-2.9.0.dist-info/entry_points.txt
undefined_bot-2.9.0.dist-info/licenses/LICENSE
undefined_bot-2.9.0.dist-info/RECORD
