Metadata-Version: 2.4
Name: Undefined-bot
Version: 2.9.0
Summary: A high-performance, highly scalable QQ group and private chat robot based on a self-developed architecture.
Project-URL: Repository, https://github.com/69gg/Undefined
Project-URL: Issues, https://github.com/69gg/Undefined/issues
Author-email: Null <pylindex@qq.com>
License-File: LICENSE
Requires-Python: >=3.10
Requires-Dist: aiofiles>=25.1.0
Requires-Dist: aiohttp>=3.13.2
Requires-Dist: apscheduler>=3.10.0
Requires-Dist: chardet>=5.2.0
Requires-Dist: crawl4ai>=0.3.0
Requires-Dist: croniter>=2.0.0
Requires-Dist: fastmcp>=2.14.4
Requires-Dist: httpx>=0.27.0
Requires-Dist: imgkit
Requires-Dist: langchain-community>=0.3.0
Requires-Dist: linkify-it-py>=2.0.3
Requires-Dist: lxml>=5.4.0
Requires-Dist: markdown-it-py[plugins]>=4.0.0
Requires-Dist: markdown>=3.10
Requires-Dist: matplotlib
Requires-Dist: mdit-py-plugins>=0.5.0
Requires-Dist: openai>=2.15.0
Requires-Dist: openpyxl>=3.1.5
Requires-Dist: pillow
Requires-Dist: playwright>=1.57.0
Requires-Dist: py7zr>=1.1.0
Requires-Dist: pymdown-extensions>=10.20
Requires-Dist: pymupdf>=1.26.7
Requires-Dist: python-docx>=1.2.0
Requires-Dist: python-dotenv>=1.0.0
Requires-Dist: python-markdown-math>=0.9
Requires-Dist: python-pptx>=1.0.2
Requires-Dist: rarfile>=4.2
Requires-Dist: rich>=14.2.0
Requires-Dist: tiktoken>=0.7.0
Requires-Dist: types-aiofiles>=25.1.0.20251011
Requires-Dist: types-markdown>=3.10.0.20251106
Requires-Dist: websockets>=12.0
Provides-Extra: ci
Requires-Dist: mypy>=1.8.0; extra == 'ci'
Requires-Dist: ruff; extra == 'ci'
Provides-Extra: dev
Requires-Dist: mypy>=1.8.0; extra == 'dev'
Requires-Dist: pytest-asyncio>=0.23.0; extra == 'dev'
Requires-Dist: pytest-cov>=5.0.0; extra == 'dev'
Requires-Dist: pytest>=8.0.0; extra == 'dev'
Requires-Dist: ruff; extra == 'dev'
